torchdataset/__init__.py
torchdataset/audiodataset.py
torchdataset/dataset.py
torchdataset/transform.py
torchdataset/visiondataset.py
torchdataset-0.1.2.dist-info/LICENSE
torchdataset-0.1.2.dist-info/WHEEL
torchdataset-0.1.2.dist-info/METADATA
torchdataset-0.1.2.dist-info/RECORD
